nlpengine/__init__.py
nlpengine/cli.py
nlpengine/utils.py
nlpengine/classifiers/__init__.py
nlpengine/classifiers/fasttext_classifier.py
nlpengine/feature_extraction/__init__.py
nlpengine/feature_extraction/word_embeddings.py
nlpengine-0.0.2.dist-info/AUTHORS.rst
nlpengine-0.0.2.dist-info/LICENSE
nlpengine-0.0.2.dist-info/METADATA
nlpengine-0.0.2.dist-info/WHEEL
nlpengine-0.0.2.dist-info/entry_points.txt
nlpengine-0.0.2.dist-info/top_level.txt
nlpengine-0.0.2.dist-info/RECORD
