Metadata-Version: 2.1
Name: nlpengine
Version: 0.0.2
Summary: A collection of Natural Language Processing tools to make your life easier.
Home-page: https://github.com/sudheesh_sudevan/nlpengine
Author: Sudheesh Sudevan
Author-email: sudheesh_sudevan@live.com
License: MIT license
Keywords: nlpengine,nlp,machine learning,natural language processing
Platform: UNKNOWN
Classifier: Development Status :: 2 - Pre-Alpha
Classifier: Intended Audience :: Developers
Classifier: License :: OSI Approved :: MIT License
Classifier: Natural Language :: English
Classifier: Programming Language :: Python :: 3.7
Classifier: Programming Language :: Python :: 3.9
Requires-Python: >=3.6
License-File: LICENSE
License-File: AUTHORS.rst
Requires-Dist: scikit-learn
Requires-Dist: pandas
Requires-Dist: fasttext (==0.9.2)
Requires-Dist: wget
Requires-Dist: python-docx
Requires-Dist: numpy
